scikit_animation/__init__.py
scikit_animation/animator.py
scikit_animation/sgdclassifier_animator.py
scikit_animation/sgdregressor_animator.py
scikit_animation-0.1.0.dist-info/METADATA
scikit_animation-0.1.0.dist-info/WHEEL
scikit_animation-0.1.0.dist-info/top_level.txt
scikit_animation-0.1.0.dist-info/RECORD
