Metadata-Version: 2.1
Name: scikit-animation
Version: 0.1.0
Summary: Library for animating scikit-learn models
Author: Parsa Toopchinezhad
License: MIT
Requires-Dist: matplotlib
Requires-Dist: numpy
Requires-Dist: scikit-learn
Requires-Dist: celluloid
